gnomepy/__init__.py
gnomepy/backtest/__init__.py
gnomepy/backtest/driver.py
gnomepy/backtest/event.py
gnomepy/backtest/exchanges/__init__.py
gnomepy/backtest/exchanges/base.py
gnomepy/backtest/exchanges/mbp/__init__.py
gnomepy/backtest/exchanges/mbp/mbp.py
gnomepy/backtest/exchanges/mbp/mbp_book.py
gnomepy/backtest/exchanges/mbp/types.py
gnomepy/backtest/fee.py
gnomepy/backtest/latency.py
gnomepy/backtest/queues/__init__.py
gnomepy/backtest/queues/base.py
gnomepy/backtest/queues/risk_averse.py
gnomepy/backtest/recorder.py
gnomepy/backtest/stats/__init__.py
gnomepy/backtest/stats/metric.py
gnomepy/backtest/stats/stats.py
gnomepy/backtest/stats/strategy.py
gnomepy/backtest/stats/utils.py
gnomepy/backtest/strategy.py
gnomepy/config.py
gnomepy/constants.py
gnomepy/data/__init__.py
gnomepy/data/cached_client.py
gnomepy/data/client.py
gnomepy/data/common.py
gnomepy/data/sbe/__init__.py
gnomepy/data/sbe/schema.xml
gnomepy/data/types.py
gnomepy/registry/__init__.py
gnomepy/registry/api.py
gnomepy/registry/types.py
gnomepy-0.1.7.dist-info/METADATA
gnomepy-0.1.7.dist-info/WHEEL
gnomepy-0.1.7.dist-info/RECORD
