Metadata-Version: 2.4
Name: gnomepy
Version: 0.1.7
Summary: 
Author: mprey
Author-email: masonprey7@gmail.com
Requires-Python: >=3.13
Classifier: Programming Language :: Python :: 3
Classifier: Programming Language :: Python :: 3.13
Classifier: Programming Language :: Python :: 3.14
Requires-Dist: bitstring (>=4.3.0,<5.0.0)
Requires-Dist: boto3 (>=1.36.18,<2.0.0)
Requires-Dist: importlib-resources (>=6.5.2,<7.0.0)
Requires-Dist: ipykernel (>=6.29.0,<7.0.0)
Requires-Dist: lxml (>=5.3.1,<6.0.0)
Requires-Dist: matplotlib (>=3.10.1,<4.0.0)
Requires-Dist: numpy (>=2.2.4,<3.0.0)
Requires-Dist: pandas (>=2.2.3,<3.0.0)
Requires-Dist: pytz (>=2025.1,<2026.0)
Requires-Dist: requests (>=2.32.3,<3.0.0)
Requires-Dist: seaborn (>=0.13.2,<0.14.0)
Requires-Dist: statsmodels (>=0.14.5,<0.15.0)
Requires-Dist: zstandard (>=0.23.0,<0.24.0)
